README.rst
setup.py
bin/relay2slack
relay2slack/__init__.py
relay2slack/relay.py
relay2slack.egg-info/PKG-INFO
relay2slack.egg-info/SOURCES.txt
relay2slack.egg-info/dependency_links.txt
relay2slack.egg-info/not-zip-safe
relay2slack.egg-info/requires.txt
relay2slack.egg-info/top_level.txt