Metadata-Version: 1.1
Name: relay2slack
Version: 0.3
Summary: relay2slack is a tool for capturing and forwarding incoming Slack webhook events
Home-page: http://github.com/blaketmiller/relay2slack
Author: Blake Miller
Author-email: blakethomasmiller@gmail.com
License: GNU GPL v2.0
Keywords: slack webhook kapacitor proxy
Platform: UNKNOWN
Classifier: Intended Audience :: Developers
Classifier: Intended Audience :: Information Technology
Classifier: License :: OSI Approved :: GNU General Public License v2 (GPLv2)
Classifier: Natural Language :: English
Classifier: Operating System :: POSIX :: Linux
Classifier: Programming Language :: Python :: 2.7
Classifier: Topic :: Software Development :: Libraries :: Python Modules
Classifier: Topic :: Utilities
